MANIFEST.in
requirements.txt
setup.py
lisa/__init__.py
lisa/plugins/__init__.py
lisa/plugins/Shopping/README.rst
lisa/plugins/Shopping/__init__.py
lisa/plugins/Shopping/shopping.json
lisa/plugins/Shopping/lang/en/LC_MESSAGES/shopping.po
lisa/plugins/Shopping/lang/fr/LC_MESSAGES/shopping.po
lisa/plugins/Shopping/modules/__init__.py
lisa/plugins/Shopping/modules/shopping.py
lisa/plugins/Shopping/web/__init__.py
lisa/plugins/Shopping/web/api.py
lisa/plugins/Shopping/web/models.py
lisa/plugins/Shopping/web/tests.py
lisa/plugins/Shopping/web/urls.py
lisa/plugins/Shopping/web/views.py
lisa_plugin_Shopping.egg-info/PKG-INFO
lisa_plugin_Shopping.egg-info/SOURCES.txt
lisa_plugin_Shopping.egg-info/dependency_links.txt
lisa_plugin_Shopping.egg-info/namespace_packages.txt
lisa_plugin_Shopping.egg-info/requires.txt
lisa_plugin_Shopping.egg-info/top_level.txt